bristlenose/__init__.py
bristlenose/__main__.py
bristlenose/cli.py
bristlenose/config.py
bristlenose/doctor.py
bristlenose/doctor_fixes.py
bristlenose/models.py
bristlenose/people.py
bristlenose/pipeline.py
bristlenose/llm/__init__.py
bristlenose/llm/client.py
bristlenose/llm/prompts.py
bristlenose/llm/structured.py
bristlenose/stages/CLAUDE.md
bristlenose/stages/__init__.py
bristlenose/stages/extract_audio.py
bristlenose/stages/identify_speakers.py
bristlenose/stages/ingest.py
bristlenose/stages/merge_transcript.py
bristlenose/stages/parse_docx.py
bristlenose/stages/parse_subtitles.py
bristlenose/stages/pii_removal.py
bristlenose/stages/quote_clustering.py
bristlenose/stages/quote_extraction.py
bristlenose/stages/render_html.py
bristlenose/stages/render_output.py
bristlenose/stages/thematic_grouping.py
bristlenose/stages/topic_segmentation.py
bristlenose/stages/transcribe.py
bristlenose/theme/CLAUDE.md
bristlenose/theme/index.css
bristlenose/theme/tokens.css
bristlenose/theme/atoms/badge.css
bristlenose/theme/atoms/bar.css
bristlenose/theme/atoms/button.css
bristlenose/theme/atoms/input.css
bristlenose/theme/atoms/logo.css
bristlenose/theme/atoms/timecode.css
bristlenose/theme/atoms/toast.css
bristlenose/theme/images/bristlenose-dark.png
bristlenose/theme/images/bristlenose.png
bristlenose/theme/js/csv-export.js
bristlenose/theme/js/editing.js
bristlenose/theme/js/favourites.js
bristlenose/theme/js/histogram.js
bristlenose/theme/js/main.js
bristlenose/theme/js/names.js
bristlenose/theme/js/player.js
bristlenose/theme/js/storage.js
bristlenose/theme/js/tags.js
bristlenose/theme/molecules/badge-row.css
bristlenose/theme/molecules/bar-group.css
bristlenose/theme/molecules/name-edit.css
bristlenose/theme/molecules/quote-actions.css
bristlenose/theme/molecules/tag-input.css
bristlenose/theme/organisms/blockquote.css
bristlenose/theme/organisms/sentiment-chart.css
bristlenose/theme/organisms/toc.css
bristlenose/theme/organisms/toolbar.css
bristlenose-0.6.2.dist-info/METADATA
bristlenose-0.6.2.dist-info/WHEEL
bristlenose-0.6.2.dist-info/entry_points.txt
bristlenose-0.6.2.dist-info/licenses/LICENSE
bristlenose-0.6.2.dist-info/RECORD
